

{
	"masterPicture": "./static/project_logo.png",
	"iconsPath": "/",
	"design": {
		"ios": {
			"pictureAspect": "backgroundAndMargin",
			"backgroundColor": "#1f2937",
			"margin": "14%",
			"assets": {
				"ios6AndPriorIcons": false,
				"ios7AndLaterIcons": false,
				"precomposedIcons": false,
				"declareOnlyDefaultIcon": true
			}
		},
		"desktopBrowser": {
			"design": "raw"
		},
		"windows": {
			"pictureAspect": "noChange",
			"backgroundColor": "#2b5797",
			"onConflict": "override",
			"assets": {
				"windows80Ie10Tile": false,
				"windows10Ie11EdgeTiles": {
					"small": false,
					"medium": true,
					"big": false,
					"rectangle": false
				}
			}
		},
		"androidChrome": {
			"pictureAspect": "noChange",
			"themeColor": "#ffffff",
			"manifest": {
				"name": "KTH Commute Finder",
				"display": "standalone",
				"orientation": "notSet",
				"onConflict": "override",
				"declared": true
			},
			"assets": {
				"legacyIcon": false,
				"lowResolutionIcons": false
			}
		},
		"safariPinnedTab": {
			"pictureAspect": "silhouette",
			"themeColor": "#1f2937"
		}
	},
	"settings": {
		"scalingAlgorithm": "Mitchell",
		"errorOnImageTooSmall": false,
		"readmeFile": false,
		"htmlCodeFile": false,
		"usePathAsIs": false
	}
}

